lessmpi/__init__.py
lessmpi/lessmpi.py
less_learn_mpi-0.1.3.dist-info/LICENSE
less_learn_mpi-0.1.3.dist-info/METADATA
less_learn_mpi-0.1.3.dist-info/WHEEL
less_learn_mpi-0.1.3.dist-info/top_level.txt
less_learn_mpi-0.1.3.dist-info/RECORD
